drugtax/__init__.py
drugtax/drugtax.py
drugtax/plotting.py
drugtax/superclasses.py
drugtax/variables.py
drugtax-1.0.14.dist-info/METADATA
drugtax-1.0.14.dist-info/WHEEL
drugtax-1.0.14.dist-info/licenses/LICENSE
drugtax-1.0.14.dist-info/RECORD
