Metadata-Version: 2.1
Name: drugtax
Version: 1.0.14
Summary: A package to characterize small ligands
Project-URL: Homepage, https://github.com/MoreiraLAB/DrugTax
Project-URL: Lab Page, http://www.moreiralab.com/
Author-email: "A.J.Preto" <martinsgomes.jose@gmail.com>, "I.S.Moreira" <irina.moreira@cnc.uc.pt>
License:                     GNU GENERAL PUBLIC LICENSE
License-File: LICENSE
Classifier: Operating System :: OS Independent
Classifier: Programming Language :: Python :: 3
Requires-Python: >=3.6
